{
  "meta": {
    "document_id": "650a39fe0fcef602bf26c0d3",
    "parent_id": "64f19816cb677b0286e74bc7",
    "name": "Multi-Channel Network (MCN)",
    "document_path": "multi-channel-network-mcn",
    "is_api_doc": false,
    "doc_type": 2,
    "update_time": "1746586760",
    "keywords": []
  },
  "detail": {
    "title": "Multi-Channel Network (MCN)",
    "content": "# What is Multi-Channel Network (MCN)?\nMulti-Channel Network (MCN) incubate and support creators within the TikTok Shop ecosystem. This type of partner supports creators in various aspects, including shoppable video content creation, shoppable livestream operations, and creator-product matchmaking for affiliate programs.\n# What are the benefits of becoming a MCN on TikTok Shop？\n**Collaboration Opportunities**\n\n* MCN members gain access to exciting collaboration opportunities with renowned sellers and brands. This opens doors to innovative and mutually beneficial partnerships.\n\n**Generous Commission**\n\n* MCN are generously rewarded for their role in acquiring, educating, and incubating creators.\n\n**Professional Growth Guidance**\n\n* Custom guidance and creator training for achieving fast growth\n\n**Custom Services**\n\n* High-performing MCN receive dedicated support, tailored to their unique needs and objectives.\n\n# How does Partner Center support MCN?\n✨ Partner Center serves as a central hub for partners to efficiently manage their business operations. Explore these essential product features designed to streamline your day-to-day activities.\n# Workflow for MCN on Partner Center\n![Image](https://p16-arcosite-sg.ibyteimg.com/tos-alisg-i-k9wyc2ijk0-sg/32f3864f9c1040d582527a308f037946~tplv-k9wyc2ijk0-image.image)\n# Feature Guide\n|  | Action | **Product Module** | **Market** | **Guide** |\n| --- | --- | --- | --- | --- |\n| 1 | Find creator on Affiliate Marketplace | Partner Console >>Creator Management>> Find creators | UK, ID,MY,VN,TH,PH,SG | [Find Creators](650a32eec16ffe02b8e4a6b8#Back%20To%20Top) on affiliate marketplace. |\n| 2 | Creator Management | Partner Console >>Creator Management>>Linked creators |  | Manage your [linked creators](650934be0fcef602bf0e5784) on Partner Center |\n| 3 | Data Compass | Partner Console>>Data Compass |  | [【MCN SEA+UK】TTSPC Data Compass Playbook](https://bytedance.feishu.cn/docx/PZYFdWlAeoYLtyx1NvgcuHsJnsf#Uk8GdWKYMoy42SxCIyIcbpsVn2e) <br> [【CAP US】TTSPC Data Compass Playbook](https://bytedance.feishu.cn/docx/NFxldJhILoty6gxE9AtcBQbAnpy?from=space_search#doxcnCbC5bilc46ihaH99x4wWRc) |\n| 4 | Product Management | Partner Console>>Products |  | [Find and manage products](650a33b1c16ffe02b8e4bce8) for creators |\n| 5 | Commission Sharing | Partner Console>>Creator Management>>Fee Agreement |  | Check [fee agreement and commission sharing with creators](650a34b4f1fd3102b9206dbc#Back%20To%20Top) |\n| 6 | Finance | Partner Console>>Finance |  | Check commissioned orders and payment on [Finance](650a33f2c16ffe02b8e4c4c4) |\n<br>\n[🚀 Become a partner today!](64f19887dc7f3e028d381064)\n\n",
    "update_time": "1746586760",
    "view_count": 0,
    "prev_document_id": "659e026753c4d402e1682ad4",
    "prev_document_path": "us-tiktok-shop-affiliate-partner-tap",
    "next_document_id": "64f19887dc7f3e028d381064",
    "next_document_path": "64f19887dc7f3e028d381064",
    "is_api_doc": false,
    "document_id": "650a39fe0fcef602bf26c0d3",
    "doc_type": 2,
    "keywords": [
      {
        "keyword": "",
        "font_color": "#141414",
        "background_color": "#E6E6E6"
      }
    ]
  }
}